zhihuisdk/__init__.py
zhihuisdk/api.py
zhihuisdk/auth.py
zhihuisdk/bll_smart_image.py
zhihuisdk/middle_samrt_api.py
zhihui_sdk_python-1.0.5.dist-info/METADATA
zhihui_sdk_python-1.0.5.dist-info/WHEEL
zhihui_sdk_python-1.0.5.dist-info/top_level.txt
zhihui_sdk_python-1.0.5.dist-info/RECORD
