Metadata-Version: 2.1
Name: zhihui-sdk-python
Version: 1.0.5
Summary: 智绘设计SDK-Python
Home-page: https://github.com/xrdpcg/zhihui-sdk-python
Author: samjinli
Author-email: samjinli@tencent.com
Classifier: Development Status :: 5 - Production/Stable
Classifier: Intended Audience :: Developers
Classifier: License :: OSI Approved :: MIT License
Classifier: Programming Language :: Python :: 3
Classifier: Programming Language :: Python :: 3.6
Classifier: Programming Language :: Python :: 3.7
Classifier: Programming Language :: Python :: 3.8
Requires-Python: >=3.6
Requires-Dist: requests
